promptcore/__init__.py
promptcore-0.0.1.dist-info/LICENSE
promptcore-0.0.1.dist-info/METADATA
promptcore-0.0.1.dist-info/WHEEL
promptcore-0.0.1.dist-info/top_level.txt
promptcore-0.0.1.dist-info/RECORD
