Metadata-Version: 2.1
Name: promptcore
Version: 0.0.1
Summary: AI Prompt Management Tool
Author-email: Will Leung <786121272@qq.com>
Project-URL: Homepage, https://github.com/leungmixin/promptcore
Project-URL: Bug Tracker, https://github.com/leungmixin/promptcore/issues
Classifier: Development Status :: 2 - Pre-Alpha
Classifier: Intended Audience :: Developers
Classifier: Programming Language :: Python :: 3
Classifier: Programming Language :: Python :: 3.8
Classifier: Programming Language :: Python :: 3.9
Classifier: Programming Language :: Python :: 3.10
Classifier: Programming Language :: Python :: 3.11
Classifier: License :: OSI Approved :: BSD License
Classifier: Operating System :: OS Independent
Classifier: Topic :: Software Development :: Libraries :: Python Modules
Classifier: Topic :: Text Processing :: General
Requires-Python: >=3.8
License-File: LICENSE
